Workbook

Sheet Léeme
A1: Modelo de costos — arquitectura Azure para pick & pack con visión (Reto 6)
A3: Qué es: costo mensual de la arquitectura propuesta en Azure y caso de negocio frente a la operación manual actual.
A4: Cómo usarlo: cambiar SOLO las celdas con texto azul de la hoja «Supuestos» (y los precios de «Precios» si cambian). Todo lo demás son fórmulas.
A5: Colores: texto azul = entrada editable · negro = fórmula · verde = dato traído de otra hoja · relleno amarillo = supuesto sin verificar.
A6: Hojas: Supuestos (entradas) · Precios (tarifas de Azure con su medidor) · Costo mensual (por componente) · Caso de negocio · Escenarios.
A7: Precios: lista de pago por uso en East US 2, tomados de la API pública de precios de Azure el 2026-10-10. Sin impuestos, descuentos ni reservas.
A8: Advertencia: las cifras laborales, de equipo y de inversión son supuestos del autor, no datos del cliente. El caso de negocio no es válido hasta sustituirlos.
A9: Documento que lo acompaña: doc/16_arquitectura_azure_y_finops.md.

Sheet Supuestos
A1: Supuestos del modelo (celdas azules = entradas editables; amarillo = supuesto sin verificar)
A3: Grupo | B3: Parámetro | C3: Valor | D3: Unidad | E3: Origen / nota
A4: Operación | B4: Líneas (estaciones) automatizadas | C4: 2 | D4: líneas | E4: Supuesto del caso base. El enunciado no fija el número de estaciones.
A5: Operación | B5: Segundos por objeto | C5: 30 | D5: s | E5: Supuesto: es el ritmo de la planta simulada del asistente. El enunciado no da la velocidad de línea.
A6: Operación | B6: Horas de operación por día | C6: 24 | D6: h | E6: Enunciado: 24 horas al día.
A7: Operación | B7: Días de operación por semana | C7: 5 | D7: días | E7: Enunciado: 5 días a la semana.
A8: Operación | B8: Semanas por año | C8: 52 | D8: semanas | E8: Calendario.
A9: Operación | B9: Turnos por día | C9: 3 | D9: turnos | E9: Enunciado: 3 turnos de 8 horas.
A10: Operación | B10: Operarios por turno por estación (hoy) | C10: 1 | D10: personas | E10: Enunciado: 1 operario por turno por estación.
A11: Operación | B11: Días de operación por mes | C11: =Supuestos!$C$7*Supuestos!$C$8/12 -> 21.666667 | D11: días | E11: Calculado.
A12: Operación | B12: Objetos por línea por mes | C12: =3600/Supuestos!$C$5*Supuestos!$C$6*Supuestos!$C$11 -> 62400 | D12: objetos | E12: Calculado.
A13: Modelo | B13: Fracción de objetos que el robot atiende solo (ACT) | C13: 0.876 | D13: fracción | E13: Resultado medido en el protocolo A (reports/results.json). En planta dependerá de la calidad de captura.
A14: Costo laboral | B14: Costo mensual cargado de un operario | C14: 600 | D14: USD/mes | E14: SUPUESTO sin verificar: sustituir por el dato de RR. HH. (salario + prestaciones).
A15: Costo laboral | B15: Personas por turno por línea para atender excepciones | C15: 0.25 | D15: FTE | E15: SUPUESTO: alguien resuelve la cola de revisión y las segundas capturas. Con 12 % de excepciones, un cuarto de jornada.
A16: Costo laboral | B16: Dedicación de ingeniería de ML y soporte | C16: 0.2 | D16: FTE | E16: SUPUESTO: monitoreo, recalibración, altas de producto.
A17: Costo laboral | B17: Costo mensual cargado de un ingeniero | C17: 2500 | D17: USD/mes | E17: SUPUESTO sin verificar.
A18: Inversión | B18: Costo único del proyecto (desarrollo, integración con el robot, piloto) | C18: 40000 | D18: USD | E18: SUPUESTO sin verificar: depende del plan de proyecto.
A19: Borde (planta) | B19: PC industrial por estación | C19: 1800 | D19: USD | E19: SUPUESTO sin verificar. No es un servicio de Azure. El modelo corre en CPU (unos 28 ms por imagen medidos).
A20: Borde (planta) | B20: Cámara e iluminación controlada por estación | C20: 1200 | D20: USD | E20: SUPUESTO sin verificar.
A21: Borde (planta) | B21: Meses de amortización del equipo | C21: 36 | D21: meses | E21: Supuesto contable.
A22: Borde (planta) | B22: Mantenimiento anual del equipo | C22: 0.1 | D22: % del costo | E22: Supuesto.
A23: Asistente | B23: Usuarios activos del asistente por línea | C23: 6 | D23: usuarios | E23: Supuesto: supervisores, calidad, mantenimiento e ingeniería en 3 turnos.
A24: Asistente | B24: Peticiones al asistente por usuario y día | C24: 8 | D24: peticiones | E24: Supuesto.
... A46: Constantes | B46: Horas por mes | C46: 730 | D46: h | E46: Convención de facturación de Azure.

Sheet Precios
A1: Precios de lista de Azure usados por el modelo (USD, región East US 2)
A2: Fuente: API pública de precios de Azure, https://prices.azure.com/api/retail/prices, consultada el 2026-10-10. Precio de lista de pago por uso, sin impuestos, descuentos ni reservas.
A4: Servicio | B4: Medidor (nombre en la API) | C4: Unidad | D4: Precio USD | E4: Verificado en la API | F4: Nota
A5: Azure Container Apps | B5: Standard vCPU Active Usage | C5: 1 segundo | D5: 2.4e-05 | E5: sí
A6: Azure Container Apps | B6: Standard vCPU Idle Usage | C6: 1 segundo | D6: 3e-06 | E6: sí
A7: Azure Container Apps | B7: Standard Memory Active Usage / Idle Usage | C7: 1 GiB-segundo | D7: 3e-06 | E7: sí
A8: Azure Container Apps | B8: Standard Requests | C8: 1 millón | D8: 0.4 | E8: sí | F8: No se descuenta la franquicia gratuita mensual del servicio: el modelo es conservador.
A9: Azure OpenAI | B9: gpt 4.1 mini Inp glbl Tokens | C9: 1.000 tokens | D9: 0.0004 | E9: sí | F9: Despliegue global. En zona de datos: 0,00044.
A10: Azure OpenAI | B10: gpt 4.1 mini cached Inp glbl Tokens | C10: 1.000 tokens | D10: 0.0001 | E10: sí
A11: Azure OpenAI | B11: gpt 4.1 mini Outp glbl Tokens | C11: 1.000 tokens | D11: 0.0016 | E11: sí | F11: En zona de datos: 0,00176.
A12: Azure OpenAI | B12: gpt 4.1 mini Inp Data Zone Tokens | C12: 1.000 tokens | D12: 0.00044 | E12: sí | F12: Los datos no salen de la zona geográfica elegida.
A13: Azure OpenAI | B13: gpt 4.1 mini Outp Data Zone Tokens | C13: 1.000 tokens | D13: 0.00176 | E13: sí
A14: Azure OpenAI | B14: gpt 4.1 nano Inp glbl Tokens | C14: 1.000 tokens | D14: 0.0001 | E14: sí | F14: Modelo más pequeño: habría que repetir la evaluación del agente antes de adoptarlo.
A15: Azure OpenAI | B15: gpt 4.1 nano Outp glbl Tokens | C15: 1.000 tokens | D15: 0.0004 | E15: sí
A16: Azure Database for PostgreSQL (servidor flexible) | B16: B1MS | C16: 1 hora | D16: 0.017 | E16: sí | F16: En Brazil South el mismo medidor cuesta 0,035: el doble.
A17: Azure Database for PostgreSQL (servidor flexible) | B17: Almacenamiento aprovisionado | C17: 1 GB-mes | D17: 0.115 | E17: NO | F17: NO verificado: la consulta a la API no devolvió este medidor. Valor de referencia; confirmar en la calculadora de Azure.
A18: Blob Storage | B18: Hot LRS Data Stored | C18: 1 GB-mes | D18: 0.0184 | E18: sí
A19: Blob Storage | B19: Hot LRS Write Operations | C19: 10.000 operaciones | D19: 0.05 | E19: sí
A20: IoT Hub | B20: S1 Unit | C20: 1 unidad-mes | D20: 25 | E20: sí | F20: El nivel básico (B1, 10 USD) no admite IoT Edge según la documentación (verificar).
A21: Container Registry | B21: Basic Registry Unit | C21: 1 día | D21: 0.1666 | E21: sí
A22: Container Registry | B22: Data Stored | C22: 1 GB-mes | D22: 0.1 | E22: sí | F22: El nivel básico incluye una cuota de almacenamiento que aquí no se descuenta.
A23: Key Vault | B23: Operations (Standard) | C23: 10.000 operaciones | D23: 0.03 | E23: sí
A24: Log Analytics | B24: Analytics Logs Data Ingestion | C24: 1 GB | D24: 2.76 | E24: sí
A25: Máquinas virtuales (cómputo de Azure ML) | B25: D4s v5 (Linux) | C25: 1 hora | D25: 0.192 | E25: sí | F25: Azure Machine Learning no cobra por el servicio, solo por el cómputo. Prioridad baja: 0,0384.
A26: Azure AI Search (opcional, no incluido) | B26: Basic Unit | C26: 1 hora | D26: 0.101 | E26: sí
A27: API Management (opcional, no incluido) | B27: Basic v2 Unit | C27: 1 hora | D27: 0.20548 | E27: sí

Sheet Costo mensual
A1: Costo mensual en Azure — caso base (USD/mes)
A3: Componente | B3: Servicio de Azure | C3: Cómo se calcula | D3: Fijo | E3: Variable por línea | F3: Total caso base
A4: Asistente (siempre encendido) | B4: Container Apps | C4: Una réplica mínima todo el mes en reposo (vCPU en reposo + memoria). Variable: CPU activa y peticiones de cada turno de conversación. | D4: =Supuestos!$C$29*Supuestos!$C$46*3600*Precios!$D$6+Supuestos!$C$30*Supuestos!$C$46*3600*Precios!$D$7 -> 11.826 | E4: =Supuestos!$C$23*Supuestos!$C$24*Supuestos!$C$11*Supuestos!$C$28*Supuestos!$C$29*(Precios!$D$5-Precios!$D$6)+Supuestos!$C$23*Supuestos!$C$24*Supuestos!$C$11/1000000*Precios!$D$8 -> 0.033176 | F4: =D4+E4*Supuestos!$C$4 -> 11.892352
A5: Modelo de lenguaje del asistente | B5: Azure OpenAI (gpt-4.1-mini) | C5: Peticiones × (entrada no cacheada + entrada cacheada + salida). Precios por 1.000 tokens. | D5: =0 -> 0 | E5: =Supuestos!$C$23*Supuestos!$C$24*Supuestos!$C$11*(Supuestos!$C$25*(1-Supuestos!$C$27)*Precios!$D$9+Supuestos!$C$25*Supuestos!$C$27*Precios!$D$10+Supuestos!$C$26*Precios!$D$11)/1000 -> 3.114592 | F5: =D5+E5*Supuestos!$C$4 -> 6.229184
A6: Visión en nube (inspecciones y staging) | B6: Container Apps, escala a cero | C6: Solo se paga mientras atiende: inspecciones × segundos × (vCPU + memoria). La inferencia de la línea corre en el borde. | D6: =0 -> 0 | E6: =Supuestos!$C$31*Supuestos!$C$34*(Supuestos!$C$32*Precios!$D$5+Supuestos!$C$33*Precios!$D$7) -> 0.03 | F6: =D6+E6*Supuestos!$C$4 -> 0.06
A7: Estado de planta, auditoría y aprobaciones | B7: PostgreSQL servidor flexible B1ms | C7: Cómputo todo el mes + almacenamiento aprovisionado. | D7: =Supuestos!$C$46*Precios!$D$16+Supuestos!$C$38*Precios!$D$17 -> 16.09 | E7: =0 -> 0 | F7: =D7+E7*Supuestos!$C$4 -> 16.09
A8: Imágenes (excepciones, muestra y reentrenamiento) | B8: Blob Storage Hot LRS | C8: Imágenes guardadas = objetos × (no ACT + muestra de ACT). GB retenidos × precio + operaciones de escritura. | D8: =0 -> 0 | E8: =Supuestos!$C$12*((1-Supuestos!$C$13)+Supuestos!$C$13*Supuestos!$C$36)*(Supuestos!$C$35/1000000*Supuestos!$C$37*Precios!$D$18+Precios!$D$19/10000) -> 0.13287895 | F8: =D8+E8*Supuestos!$C$4 -> 0.26575791
A9: Telemetría y despliegue al borde | B9: IoT Hub S1 + IoT Edge | C9: Unidades × precio. El runtime de IoT Edge no tiene costo. Una unidad cubre holgadamente decenas de líneas. | D9: =Supuestos!$C$45*Precios!$D$20 -> 25 | E9: =0 -> 0 | F9: =D9+E9*Supuestos!$C$4 -> 25
A10: Registro de imágenes de contenedor | B10: Container Registry Basic | C10: Unidad diaria × 365/12 + GB almacenados. | D10: =Precios!$D$21*365/12+Supuestos!$C$43*Precios!$D$22 -> 6.0674167 | E10: =0 -> 0 | F10: =D10+E10*Supuestos!$C$4 -> 6.0674167
A11: Secretos | B11: Key Vault Standard | C11: Operaciones / 10.000 × precio. | D11: =Supuestos!$C$44/10000*Precios!$D$23 -> 0.3 | E11: =0 -> 0 | F11: =D11+E11*Supuestos!$C$4 -> 0.3
A12: Registros y monitoreo | B12: Log Analytics + Application Insights | C12: GB ingeridos por encima de la franquicia × precio. La parte por línea se cobra completa (la franquicia se consume con la parte fija). | D12: =MAX(0,Supuestos!$C$39-Supuestos!$C$41)*Precios!$D$24 -> 0 | E12: =IF(Supuestos!$C$39>=Supuestos!$C$41,Supuestos!$C$40,MAX(0,Supuestos!$C$40-(Supuestos!$C$41-Supuestos!$C$39)/Supuestos!$C$4))*Precios!$D$24 -> 4.14 | F12: =D12+E12*Supuestos!$C$4 -> 8.28
A13: Entrenamiento y registro de modelos | B13: Azure Machine Learning (cómputo D4s v5) | C13: Horas de cómputo × precio. El clúster escala a cero entre trabajos. | D13: =Supuestos!$C$42*Precios!$D$25 -> 1.92 | E13: =0 -> 0 | F13: =D13+E13*Supuestos!$C$4 -> 1.92
A14: Total Azure | C14: Suma de los componentes. Precio de lista, sin impuestos ni descuentos. | D14: =SUM(D4:D13) -> 61.203417 | E14: =SUM(E4:E13) -> 7.450647 | F14: =SUM(F4:F13) -> 76.104711
A16: Equipo en planta (no es Azure)
A17: Componente | B17: Qué es | C17: Cómo se calcula | D17: Fijo | E17: Variable por línea | F17: Total caso base
A18: PC industrial, cámara e iluminación | B18: Equipo propio en cada estación | C18: (PC + cámara) / meses de amortización + mantenimiento anual / 12. | D18: =0 -> 0 | E18: =(Supuestos!$C$19+Supuestos!$C$20)/Supuestos!$C$21+(Supuestos!$C$19+Supuestos!$C$20)*Supuestos!$C$22/12 -> 108.33333 | F18: =D18+E18*Supuestos!$C$4 -> 216.66667
A20: Opcionales no incluidos (para el análisis de trade-offs)
A21: Búsqueda de procedimientos gestionada | B21: Azure AI Search Basic | C21: Unidad × horas del mes. No se incluye: con 6 procedimientos, la búsqueda léxica en proceso basta. | D21: =Supuestos!$C$46*Precios!$D$26 -> 73.73 | F21: =D21 -> 73.73
A22: Pasarela de API con cuotas por usuario | B22: API Management Basic v2 | C22: Unidad × horas del mes. No se incluye a esta escala; se justifica con varias plantas. | D22: =Supuestos!$C$46*Precios!$D$27 -> 150.0004 | F22: =D22 -> 150.0004
A24: No modelado: red privada (private endpoints, VPN o ExpressRoute), Microsoft Entra ID (se asume inquilino existente), copias de seguridad adicionales, soporte de Azure, impuestos y tráfico de salida.

Sheet Caso de negocio
A1: Caso de negocio — operación actual frente a la automatizada (USD/mes, caso base)
A3: Concepto | B3: USD/mes | C3: Cómo se calcula
A4: OPERACIÓN ACTUAL
A5: Operarios de identificación y alineación | B5: =Supuestos!$C$4*Supuestos!$C$9*Supuestos!$C$10*Supuestos!$C$14 -> 3600 | C5: Líneas × turnos × operarios por turno × costo mensual.
A6: OPERACIÓN AUTOMATIZADA
A7: Azure | B7: ='Costo mensual'!$F$14 -> 76.104711 | C7: Hoja «Costo mensual».
A8: Equipo en planta (amortización y mantenimiento) | B8: ='Costo mensual'!$F$18 -> 216.66667 | C8: Hoja «Costo mensual».
A9: Personal para excepciones (revisión y segundas capturas) | B9: =Supuestos!$C$4*Supuestos!$C$9*Supuestos!$C$15*Supuestos!$C$14 -> 900 | C9: Líneas × turnos × fracción de jornada × costo mensual.
A10: Ingeniería de ML y soporte | B10: =Supuestos!$C$16*Supuestos!$C$17 -> 500 | C10: Dedicación × costo mensual.
A11: Total operación automatizada | B11: =SUM(B7:B10) -> 1692.7714 | C11: Suma de los cuatro conceptos.
A13: Ahorro mensual | B13: =B5-B11 -> 1907.2286 | C13: Actual − automatizada. Negativo significa que automatizar cuesta más.
A14: Ahorro mensual (%) | B14: =IF(B5=0,0,(B5-B11)/B5) -> 0.52978573 | C14: Sobre el costo actual.
A15: Inversión única del proyecto | B15: =Supuestos!$C$18 -> 40000 | C15: Hoja «Supuestos».
A16: Meses para recuperar la inversión | B16: =IF(B5-B11<=0,"no se recupera",Supuestos!$C$18/(B5-B11)) -> 20.97284 | C16: Inversión / ahorro mensual.
A17: Objetos procesados por mes | B17: =Supuestos!$C$12*Supuestos!$C$4 -> 124800 | C17: Objetos por línea × líneas.
A18: Costo de Azure por cada 1.000 objetos | B18: =IF(Supuestos!$C$12*Supuestos!$C$4=0,0,'Costo mensual'!$F$14/(Supuestos!$C$12*Supuestos!$C$4)*1000) -> 0.60981339 | C18: Indicador unitario de FinOps.
A19: Costo total automatizado por cada 1.000 objetos | B19: =IF(Supuestos!$C$12*Supuestos!$C$4=0,0,B11/(Supuestos!$C$12*Supuestos!$C$4)*1000) -> 13.563873 | C19: Incluye personas y equipo.
A20: Costo actual por cada 1.000 objetos | B20: =IF(Supuestos!$C$12*Supuestos!$C$4=0,0,B5/(Supuestos!$C$12*Supuestos!$C$4)*1000) -> 28.846154 | C20: Referencia.
A21: Peso de Azure en el costo automatizado | B21: =IF(B11=0,0,B7/B11) -> 0.044958647 | C21: Cuánto del costo recurrente es nube.
A23: El resultado depende sobre todo de tres supuestos sin verificar (amarillos en «Supuestos»): el costo del operario, el personal que queda para excepciones y la inversión del proyecto. Sustituirlos antes de usar la cifra.

Sheet Escenarios
A1: Escenarios — cómo escala el costo con el número de líneas (USD/mes)
A3: Líneas | B3: Azure | C3: Azure por línea | D3: Equipo en planta | E3: Personas (excepciones + ingeniería) | F3: Total automatizado | G3: Operación actual | H3: Ahorro mensual | I3: Meses para recuperar
A4: 1 | B4: ='Costo mensual'!$D$14+'Costo mensual'!$E$14*A4 -> 68.654064 | C4: =B4/A4 -> 68.654064 | D4: ='Costo mensual'!$E$18*A4 -> 108.33333 | E4: =A4*Supuestos!$C$9*Supuestos!$C$15*Supuestos!$C$14+Supuestos!$C$16*Supuestos!$C$17 -> 950 | F4: =B4+D4+E4 -> 1126.9874 | G4: =A4*Supuestos!$C$9*Supuestos!$C$10*Supuestos!$C$14 -> 1800 | H4: =G4-F4 -> 673.0126 | I4: =IF(H4<=0,"no se recupera",Supuestos!$C$18/H4) -> 59.434251
A5: 2 | B5: ='Costo mensual'!$D$14+'Costo mensual'!$E$14*A5 -> 76.104711 | C5: =B5/A5 -> 38.052355 | D5: ='Costo mensual'!$E$18*A5 -> 216.66667 | E5: =A5*Supuestos!$C$9*Supuestos!$C$15*Supuestos!$C$14+Supuestos!$C$16*Supuestos!$C$17 -> 1400 | F5: =B5+D5+E5 -> 1692.7714 | G5: =A5*Supuestos!$C$9*Supuestos!$C$10*Supuestos!$C$14 -> 3600 | H5: =G5-F5 -> 1907.2286 | I5: =IF(H5<=0,"no se recupera",Supuestos!$C$18/H5) -> 20.97284
A6: 5 | B6: ='Costo mensual'!$D$14+'Costo mensual'!$E$14*A6 -> 98.456651 | C6: =B6/A6 -> 19.69133 | D6: ='Costo mensual'!$E$18*A6 -> 541.66667 | E6: =A6*Supuestos!$C$9*Supuestos!$C$15*Supuestos!$C$14+Supuestos!$C$16*Supuestos!$C$17 -> 2750 | F6: =B6+D6+E6 -> 3390.1233 | G6: =A6*Supuestos!$C$9*Supuestos!$C$10*Supuestos!$C$14 -> 9000 | H6: =G6-F6 -> 5609.8767 | I6: =IF(H6<=0,"no se recupera",Supuestos!$C$18/H6) -> 7.1302815
A7: 10 | B7: ='Costo mensual'!$D$14+'Costo mensual'!$E$14*A7 -> 135.70989 | C7: =B7/A7 -> 13.570989 | D7: ='Costo mensual'!$E$18*A7 -> 1083.3333 | E7: =A7*Supuestos!$C$9*Supuestos!$C$15*Supuestos!$C$14+Supuestos!$C$16*Supuestos!$C$17 -> 5000 | F7: =B7+D7+E7 -> 6219.0432 | G7: =A7*Supuestos!$C$9*Supuestos!$C$10*Supuestos!$C$14 -> 18000 | H7: =G7-F7 -> 11780.957 | I7: =IF(H7<=0,"no se recupera",Supuestos!$C$18/H7) -> 3.39531
A8: 20 | B8: ='Costo mensual'!$D$14+'Costo mensual'!$E$14*A8 -> 210.21636 | C8: =B8/A8 -> 10.510818 | D8: ='Costo mensual'!$E$18*A8 -> 2166.6667 | E8: =A8*Supuestos!$C$9*Supuestos!$C$15*Supuestos!$C$14+Supuestos!$C$16*Supuestos!$C$17 -> 9500 | F8: =B8+D8+E8 -> 11876.883 | G8: =A8*Supuestos!$C$9*Supuestos!$C$10*Supuestos!$C$14 -> 36000 | H8: =G8-F8 -> 24123.117 | I8: =IF(H8<=0,"no se recupera",Supuestos!$C$18/H8) -> 1.6581605
A10: Se mantienen constantes la inversión del proyecto y la dedicación de ingeniería: es una simplificación. Con más líneas, ambas crecerían, aunque menos que proporcionalmente.
A13: Sensibilidad del modelo de lenguaje (caso base de líneas)
A14: Opción | B14: USD/mes | E14: Qué cambia
A15: gpt-4.1-mini, despliegue global (base) | B15: =Supuestos!$C$23*Supuestos!$C$24*Supuestos!$C$11*Supuestos!$C$4*(Supuestos!$C$25*Precios!$D$9+Supuestos!$C$26*Precios!$D$11)/1000 -> 6.229184 | E15: El del modelo de costos, sin caché.
A16: gpt-4.1-mini, zona de datos | B16: =Supuestos!$C$23*Supuestos!$C$24*Supuestos!$C$11*Supuestos!$C$4*(Supuestos!$C$25*Precios!$D$12+Supuestos!$C$26*Precios!$D$13)/1000 -> 6.8521024 | E16: Los datos no salen de la zona geográfica: +10 %.
A17: gpt-4.1-mini con el 50 % de la entrada en caché | B17: =Supuestos!$C$23*Supuestos!$C$24*Supuestos!$C$11*Supuestos!$C$4*(Supuestos!$C$25*0.5*Precios!$D$9+Supuestos!$C$25*0.5*Precios!$D$10+Supuestos!$C$26*Precios!$D$11)/1000 -> 4.112888 | E17: Instrucciones y contratos de tools repetidos en cada llamada.
A18: gpt-4.1-nano, despliegue global | B18: =Supuestos!$C$23*Supuestos!$C$24*Supuestos!$C$11*Supuestos!$C$4*(Supuestos!$C$25*Precios!$D$14+Supuestos!$C$26*Precios!$D$15)/1000 -> 1.557296 | E18: Cuatro veces más barato; exige repetir la evaluación del agente.
